{
  "id": "/organization",
  "title": "Organization",
  "description": "Organization object in Wice CRM",
  "type": "object",

  "definitions": {
    "rowid": {
      "type": "number",
      "description": "Rowid",
      "example": "197775"
    },
    "name": {
      "type": "string",
      "description": "Name",
      "example": "Your Compnay Ltd."
    },
    "street": {
      "type": "string",
      "description": "Street",
      "example": "Main Street"
    },
    "street_number": {
      "type": "string",
      "description": "Street number",
      "example": "124"
    },
    "zip_code": {
      "type": "string",
      "description": "Zip code",
      "example": "29610"
    },
    "town": {
      "type": "string",
      "description": "Town",
      "example": "London"
    },
    "state": {
      "type": "string",
      "description": "State",
      "example": "London District"
    },
    "country": {
      "type": "string",
      "description": "Country",
      "example": "Great Britain"
    },
    "phone": {
      "type": "string",
      "description": "Phone",
      "example": "+44 20 9812 0574"
    },
    "fax": {
      "type": "string",
      "description": "Fax",
      "example": "+44 20 9812 0590"
    },
    "email": {
      "type": "string",
      "description": "Email",
      "example": "yourcompany@mail.com"
    },
    "url": {
      "type": "string",
      "description": "Url",
      "example": "www.yourcompany.com"
    },
    "updated_name": {
      "type": "string",
      "description": "Updated organization's name",
      "example": "Big Company Ltd"
    }
  },
  "required": [
    "organizationName"
  ],
  "properties": {
    "rowid": {
      "$ref": "#/definitions/rowid"
    },
    "name": {
      "$ref": "#/definitions/name"
    },
    "street": {
      "$ref": "#/definitions/street"
    },
    "street_number": {
      "$ref": "#/definitions/street_number"
    },
    "zip_code": {
      "$ref": "#/definitions/zip_code"
    },
    "town": {
      "$ref": "#/definitions/town"
    },
    "state": {
      "$ref": "#/definitions/state"
    },
    "country": {
      "$ref": "#/definitions/country"
    },
    "phone": {
      "$ref": "#/definitions/phone"
    },
    "fax": {
      "$ref": "#/definitions/fax"
    },
    "email": {
      "$ref": "#/definitions/email"
    },
    "url": {
      "$ref": "#/definitions/url"
    }
  },

  "links": [{
      "title": "Get a single organization",
      "description": "Get a single organization saved by a specific user",
      "rel": "instances",
      "href": "plugin/wp_elasticio_backend/json",
      "method": "GET",
      "authentication_needed": true,
      "schema": {
        "type": "object",
        "properties": {
          "method": {
            "type": "string",
            "description": "Method get_company in Wice",
            "example": "get_company"
          },
          "cookie": {
            "type": "string",
            "description": "Cookie",
            "example": "dqerpzf8bpj7yoc9kryzbf8zx8e4funj"
          },
          "pkey": {
            "type": "string",
            "description": "Rowid",
            "example": "197775"
          }
        }
      },
      "targetSchema": {
        "type": "object",
        "properties": {
          "rowid": {
            "$ref": "#/definitions/rowid"
          },
          "name": {
            "$ref": "#/definitions/name"
          },
          "street": {
            "$ref": "#/definitions/street"
          },
          "street_number": {
            "$ref": "#/definitions/street_number"
          },
          "zip_code": {
            "$ref": "#/definitions/zip_code"
          },
          "town": {
            "$ref": "#/definitions/town"
          },
          "state": {
            "$ref": "#/definitions/state"
          },
          "country": {
            "$ref": "#/definitions/country"
          },
          "phone": {
            "$ref": "#/definitions/phone"
          },
          "fax": {
            "$ref": "#/definitions/fax"
          },
          "email": {
            "$ref": "#/definitions/email"
          },
          "url": {
            "$ref": "#/definitions/url"
          }
        }
      }
    },
    {
      "title": "Get all organizations",
      "description": "Get all organizations",
      "rel": "self",
      "href": "plugin/wp_elasticio_backend/json",
      "method": "GET",
      "authentication_needed": true,
      "schema": {
        "type": "object",
        "properties": {
          "method": {
            "type": "string",
            "description": "Method get_all_companies in Wice",
            "example": "get_all_companies"
          },
          "cookie": {
            "type": "string",
            "description": "Cookie",
            "example": "dqerpzf8bpj7yoc9kryzbf8zx8e4funj"
          }
        }
      },
      "targetSchema": {
        "type": "array",
        "items": {
          "properties": {
            "rowid": {
              "$ref": "#/definitions/rowid"
            },
            "name": {
              "$ref": "#/definitions/name"
            },
            "street": {
              "$ref": "#/definitions/street"
            },
            "street_number": {
              "$ref": "#/definitions/street_number"
            },
            "zip_code": {
              "$ref": "#/definitions/zip_code"
            },
            "town": {
              "$ref": "#/definitions/town"
            },
            "state": {
              "$ref": "#/definitions/state"
            },
            "country": {
              "$ref": "#/definitions/country"
            },
            "phone": {
              "$ref": "#/definitions/phone"
            },
            "fax": {
              "$ref": "#/definitions/fax"
            },
            "email": {
              "$ref": "#/definitions/email"
            },
            "url": {
              "$ref": "#/definitions/url"
            }
          }
        }
      }
    },
    {
      "title": "Create organization",
      "description": "To create an organization you have to pass organization's name.",
      "rel": "instances",
      "href": "plugin/wp_elasticio_backend/json",
      "method": "POST",
      "authentication_needed": true,
      "required": ["name"],
      "schema": {
        "type": "object",
        "properties": {
          "method": {
            "type": "string",
            "description": "Method insert_company in Wice",
            "example": "insert_company"
          },
          "cookie": {
            "type": "string",
            "description": "Cookie",
            "example": "dqerpzf8bpj7yoc9kryzbf8zx8e4funj"
          },
          "data": {
            "type": "string",
            "description": "Organization's name",
            "example": {
              "name": "Your Compnay Ltd."
            }
          }
        }
      },
      "targetSchema": {
        "type": "object",
        "properties": {
          "rowid": {
            "$ref": "#/definitions/rowid"
          },
          "name": {
            "$ref": "#/definitions/name"
          }
        }
      }
    },
    {
      "title": "Update organization",
      "description": "To update an organization you need the pass organization rowid and the field whitch you want to update.",
      "rel": "instances",
      "href": "plugin/wp_elasticio_backend/json",
      "method": "POST",
      "authentication_needed": true,
      "required": ["rowid"],
      "schema": {
        "type": "object",
        "properties": {
          "method": {
            "type": "string",
            "description": "Method update_company in Wice",
            "example": "update_company"
          },
          "cookie": {
            "type": "string",
            "description": "Cookie",
            "example": "dqerpzf8bpj7yoc9kryzbf8zx8e4funj"
          },
          "data": {
            "type": "string",
            "description": "Organization's name",
            "example": {
              "rowid": "197775",
              "name": "Big Company Ltd"
            }
          }
        }
      },
      "targetSchema": {
        "type": "object",
        "properties": {
          "rowid": {
            "$ref": "#/definitions/rowid"
          },
          "name": {
            "$ref": "#/definitions/updated_name"
          },
          "street": {
            "$ref": "#/definitions/street"
          },
          "street_number": {
            "$ref": "#/definitions/street_number"
          },
          "zip_code": {
            "$ref": "#/definitions/zip_code"
          },
          "town": {
            "$ref": "#/definitions/town"
          },
          "state": {
            "$ref": "#/definitions/state"
          },
          "country": {
            "$ref": "#/definitions/country"
          },
          "phone": {
            "$ref": "#/definitions/phone"
          },
          "fax": {
            "$ref": "#/definitions/fax"
          },
          "email": {
            "$ref": "#/definitions/email"
          },
          "url": {
            "$ref": "#/definitions/url"
          }
        }
      }
    },
    {
      "title": "Delete organization",
      "description": "To delete an organization you have to pass organization's rowid, which you want to delete. We do NOT really delete the person from our database, we just update the value in field is_deleted to 1 which actually hides the person from the view.",
      "rel": "instances",
      "href": "plugin/wp_elasticio_backend/json",
      "method": "POST",
      "authentication_needed": true,
      "required": ["rowid"],
      "schema": {
        "type": "object",
        "properties": {
          "method": {
            "type": "string",
            "description": "Method delete_company in Wice",
            "example": "delete_company"
          },
          "cookie": {
            "type": "string",
            "description": "Cookie",
            "example": "dqerpzf8bpj7yoc9kryzbf8zx8e4funj"
          },
          "data": {
            "type": "string",
            "description": "Organization's rowid which must be deleted",
            "example": {
              "rowid": "197775"
            }
          }
        }
      },
      "targetSchema": {
        "type": "object",
        "properties": {
          "rowid": {
            "$ref": "#/definitions/rowid"
          },
          "name": {
            "$ref": "#/definitions/name"
          }
        }
      }
    }
  ]
}
